hip_data_ml_utils/core/__init__.py
hip_data_ml_utils/core/config.py
hip_data_ml_utils/core/databricks_utils.py
hip_data_ml_utils/core/pyathena_utils.py
hip_data_ml_utils/databricks_client/__init__.py
hip_data_ml_utils/databricks_client/client.py
hip_data_ml_utils/databricks_client/databricks-sql.ipynb
hip_data_ml_utils/mlflow_databricks/__init__.py
hip_data_ml_utils/mlflow_databricks/mlflow_model_utils.py
hip_data_ml_utils/mlflow_databricks/mlflow_prediction_requests.py
hip_data_ml_utils/mlflow_databricks/mlflow_serve.py
hip_data_ml_utils/mlflow_databricks/mlflow_tracker.py
hip_data_ml_utils/pyathena_client/__init__.py
hip_data_ml_utils/pyathena_client/client.py
hip_data_ml_utils-1.4.7.dist-info/LICENSE.txt
hip_data_ml_utils-1.4.7.dist-info/METADATA
hip_data_ml_utils-1.4.7.dist-info/WHEEL
hip_data_ml_utils-1.4.7.dist-info/RECORD
