Metadata-Version: 2.1
Name: hip_data_ml_utils
Version: 1.4.7
Summary: Common Python tools and utilities for Hipages ML work
License: MIT
Author: Hipages Tradie Marketplace Experience
Author-email: shumingpeh@hipagesgroup.com.au
Requires-Python: >=3.9,<3.13
Classifier: License :: OSI Approved :: MIT License
Classifier: Programming Language :: Python :: 3
Classifier: Programming Language :: Python :: 3.9
Classifier: Programming Language :: Python :: 3.10
Classifier: Programming Language :: Python :: 3.11
Classifier: Programming Language :: Python :: 3.12
Requires-Dist: PyYAML (==6.0)
Requires-Dist: Werkzeug (>=3.0.3,<4.0.0)
Requires-Dist: aiobotocore (>=2.8.0,<3.0.0)
Requires-Dist: appdirs (==1.4.4)
Requires-Dist: attrs (>=22.2.0,<23.0.0)
Requires-Dist: black (>=22.6.0,<23.0.0)
Requires-Dist: boto3 (>=1.33.5,<2.0.0)
Requires-Dist: botocore (>=1.34.15,<2.0.0)
Requires-Dist: certifi (>=2023.7.22,<2024.0.0)
Requires-Dist: cfgv (==3.2.0)
Requires-Dist: coverage (==5.4)
Requires-Dist: databricks-sql-connector (>=3.3.0,<4.0.0)
Requires-Dist: distlib (>=0.3.8,<0.4.0)
Requires-Dist: filelock (>=3.14.0,<4.0.0)
Requires-Dist: flake8 (>=4.0.1,<5.0.0)
Requires-Dist: identify (==1.5.13)
Requires-Dist: iniconfig (==1.1.1)
Requires-Dist: isort (>=5.10.1,<6.0.0)
Requires-Dist: joblib (==1.2.0)
Requires-Dist: mccabe (==0.6.1)
Requires-Dist: mlflow (==2.22.0)
Requires-Dist: mock (>=4.0.3,<5.0.0)
Requires-Dist: moto (>=4.2.7,<5.0.0)
Requires-Dist: mypy-extensions (==0.4.3)
Requires-Dist: nodeenv (>=1.5.0,<2.0.0)
Requires-Dist: numpy (==1.26.4)
Requires-Dist: packaging (>=23.1,<24.0)
Requires-Dist: pandas (==2.2.3)
Requires-Dist: pluggy (==1.5.0)
Requires-Dist: polling (==0.3.2)
Requires-Dist: py (>=1.11.0,<2.0.0)
Requires-Dist: pyarrow (>=14.0.1,<15.0.0)
Requires-Dist: pyathena (>=2.25.2,<3.0.0)
Requires-Dist: pydantic (>=2.11.3,<3.0.0)
Requires-Dist: pydantic-settings (>=2.9.1,<3.0.0)
Requires-Dist: pyparsing (==2.4.7)
Requires-Dist: pytest (>=8.3.3,<9.0.0)
Requires-Dist: pytest-cov (>=3.0.0,<4.0.0)
Requires-Dist: pytest-custom-exit-code (==0.3.0)
Requires-Dist: regex (>=2024.9.11,<2025.0.0)
Requires-Dist: requests (>=2.32.0,<3.0.0)
Requires-Dist: responses (==0.23.1)
Requires-Dist: s3fs (>=2023.10.0,<2024.0.0)
Requires-Dist: six (==1.15.0)
Requires-Dist: toml (==0.10.2)
Requires-Dist: torch (==2.3.1)
Requires-Dist: typed-ast (>=1.5.3,<2.0.0)
Requires-Dist: typing-extensions (>=4.4.0,<5.0.0)
